Workbook
Name sugestao_investimento: Planilha2!$C$15
Name qtd_anos: Planilha2!$C$20
Name patrimonio: Planilha2!$C$22
Name Rendimento_carteira: Planilha2!$C$14
Name salario: Planilha2!$C$13
Name aporte: Planilha2!$C$19
Name taxa_mensal: Planilha2!$C$21

Sheet Planilha2
B12: CONFIGURAÇÕES
B13: Salário | C13: 5000
B14: Rendimento Carteira | C14: 0.006
B15: Sugestão de Investimento (30%) | C15: =C13*30% -> 1500
B18: INVESTIMENTO MENSAL
B19: Quanto investir por mês? | C19: 1200
B20: Por quantos anos? | C20: 10
B21: Taxa Rendimento mensal? | C21: 0.01079
B22: Patrimônio acumulado? | C22: =FV(taxa_mensal,qtd_anos*12,aporte*-1) -> 291941.05
B23: Dividendos Mensais? | C23: =patrimonio*Rendimento_carteira -> 1751.6463
B25: Cenários | D25: Dividendo
A26: 2 | B26: Quanto teria em 2 anos? | C26: =FV($C$21,$A26*12,$C$19*-1) -> 32673.153 | D26: =C26*Rendimento_carteira -> 196.03892
A27: 5 | B27: Quanto teria em 5 anos? | C27: =FV($C$21,A$27*12,$C$19*-1) -> 100532.3 | D27: =C27*Rendimento_carteira -> 603.19378
A28: 10 | B28: Quanto teria em 10 anos? | C28: =FV($C$21,A$28*12,$C$19*-1) -> 291941.05 | D28: =C28*Rendimento_carteira -> 1751.6463
A29: 20 | B29: Quanto teria em 20 anos? | C29: =FV($C$21,$A$29*12,$C$19*-1) -> 1350238.1 | D29: =C29*Rendimento_carteira -> 8101.4285
A30: 30 | B30: Quanto teria em 30 anos? | C30: =FV($C$21,$A$30*12,$C$19*-1) -> 5186603.6 | D30: =C30*Rendimento_carteira -> 31119.622
B32: PERFIL | C32: Conservador
B33: VALOR A SER INVESTIDO POR MÊS | C33: 250
B35: TIPO DE FII | C35: Percentual Sugerido | D35: Valores
B36: PAPEL | C36: =VLOOKUP($C$32&"-"&B36,'Planilha-apoio'!$A:$D,4,) -> 0.3 | D36: =C36*$C$33 -> 75
B37: TIJOLO | C37: =VLOOKUP($C$32&"-"&B37,'Planilha-apoio'!$A:$D,4,) -> 0.5 | D37: =C37*$C$33 -> 125
B38: HIBRIDOS | C38: =VLOOKUP($C$32&"-"&B38,'Planilha-apoio'!$A:$D,4,) -> 0.1 | D38: =C38*$C$33 -> 25
B39: FOFs | C39: =VLOOKUP($C$32&"-"&B39,'Planilha-apoio'!$A:$D,4,) -> 0.1 | D39: =C39*$C$33 -> 25
B40: DESENVOLVIMENTO | C40: =VLOOKUP($C$32&"-"&B40,'Planilha-apoio'!$A:$D,4,) -> 0 | D40: =C40*$C$33 -> 0
B41: HOTELARIAS | C41: =VLOOKUP($C$32&"-"&B41,'Planilha-apoio'!$A:$D,4,) -> 0 | D41: =C41*$C$33 -> 0
D42: =C42*$C$33 -> 0

Sheet Sobre Investimentos
B2: O que são investimentos?
B4: Investir é colocar seu dinheiro para trabalhar por você, em vez de deixá-lo parado. Em termos simples: você guarda uma parte do que ganha e aplica em algo que tem potencial de gerar retorno ao longo do tempo — seja um rendimento fixo, seja a valorização de um bem ou negócio. É diferente de poupar: poupar é guardar; investir é fazer esse valor crescer.
B6: Por que começar a investir?
B7: Guardar dinheiro na poupança ou embaixo do colchão praticamente não gera retorno real — a inflação corrói o poder de compra ao longo dos anos. Investir, mesmo com valores pequenos e de forma constante, é o que permite construir patrimônio, ter uma reserva para imprevistos e, no futuro, gerar uma renda extra ou complementar à aposentadoria.
B9: Motivos para investir
B10: • Proteger o seu dinheiro da inflação, que reduz o poder de compra ao longo do tempo.
B11: • Ter uma reserva para imprevistos, sem precisar recorrer a empréstimos ou ao cartão.
B12: • Fazer os juros compostos trabalharem por você: quanto mais cedo você começa, maior o efeito.
B13: • Criar uma renda extra, como os dividendos mensais dos fundos imobiliários.
B14: • Realizar objetivos: viagem, casa própria, estudos, negócio próprio.
B15: • Ter tranquilidade e liberdade de escolha no futuro, inclusive na aposentadoria.
B17: Independência financeira
... B44: Aviso: este material é educativo e não constitui recomendação de investimento.

Sheet Metas de Vida
B2: Metas de Vida
B3: Escolha seus objetivos e descubra quanto guardar por mês para chegar lá. Troque os exemplos pelas suas metas: o resto calcula sozinho.
B5: Como ler as cores | D5: Dados vindos da Planilha2
B6: Lilás, letra azul: preencha você | D6: Rendimento mensal | F6: =Planilha2!C21 -> 0.01079
B7: Letra verde: vem da aba Planilha2 | D7: Salário | F7: =Planilha2!C13 -> 5000
B8: Letra preta: cálculo automático | D8: Sugestão de investimento (30%) | F8: =Planilha2!C15 -> 1500
B10: Minha meta | C10: Valor que quero juntar | D10: Em quantos anos? | E10: Quanto guardar por mês | F10: Quanto sai do meu bolso | G10: Rendimento estimado | H10: % do salário
B11: Viagem dos sonhos | C11: 8000 | D11: 2 | E11: =IF(OR(C11="",D11="",D11<=0),"",-PMT($F$6,D11*12,0,C11)) -> 293.81921 | F11: =IF(E11="","",E11*D11*12) -> 7051.6611 | G11: =IF(E11="","",C11-F11) -> 948.33891 | H11: =IF(OR(E11="",$F$7<=0),"",E11/$F$7) -> 0.058763842
B12: Reserva de emergência | C12: 15000 | D12: 3 | E12: =IF(OR(C12="",D12="",D12<=0),"",-PMT($F$6,D12*12,0,C12)) -> 343.18367 | F12: =IF(E12="","",E12*D12*12) -> 12354.612 | G12: =IF(E12="","",C12-F12) -> 2645.3881 | H12: =IF(OR(E12="",$F$7<=0),"",E12/$F$7) -> 0.068636733
B13: Entrada da casa própria | C13: 40000 | D13: 8 | E13: =IF(OR(C13="",D13="",D13<=0),"",-PMT($F$6,D13*12,0,C13)) -> 239.52727 | F13: =IF(E13="","",E13*D13*12) -> 22994.618 | G13: =IF(E13="","",C13-F13) -> 17005.382 | H13: =IF(OR(E13="",$F$7<=0),"",E13/$F$7) -> 0.047905454
B14: Meu negócio | C14: 20000 | D14: 5 | E14: =IF(OR(C14="",D14="",D14<=0),"",-PMT($F$6,D14*12,0,C14)) -> 238.72925 | F14: =IF(E14="","",E14*D14*12) -> 14323.755 | G14: =IF(E14="","",C14-F14) -> 5676.2449 | H14: =IF(OR(E14="",$F$7<=0),"",E14/$F$7) -> 0.04774585
B15: Aposentadoria tranquila | C15: 500000 | D15: 25 | E15: =IF(OR(C15="",D15="",D15<=0),"",-PMT($F$6,D15*12,0,C15)) -> 224.60789 | F15: =IF(E15="","",E15*D15*12) -> 67382.367 | G15: =IF(E15="","",C15-F15) -> 432617.63 | H15: =IF(OR(E15="",$F$7<=0),"",E15/$F$7) -> 0.044921578
E16: =IF(OR(C16="",D16="",D16<=0),"",-PMT($F$6,D16*12,0,C16)) | F16: =IF(E16="","",E16*D16*12) | G16: =IF(E16="","",C16-F16) | H16: =IF(OR(E16="",$F$7<=0),"",E16/$F$7)
E17: =IF(OR(C17="",D17="",D17<=0),"",-PMT($F$6,D17*12,0,C17)) | F17: =IF(E17="","",E17*D17*12) | G17: =IF(E17="","",C17-F17) | H17: =IF(OR(E17="",$F$7<=0),"",E17/$F$7)
E18: =IF(OR(C18="",D18="",D18<=0),"",-PMT($F$6,D18*12,0,C18)) | F18: =IF(E18="","",E18*D18*12) | G18: =IF(E18="","",C18-F18) | H18: =IF(OR(E18="",$F$7<=0),"",E18/$F$7)
B19: TOTAL POR MÊS | E19: =SUM(E11:E18) -> 1339.8673 | H19: =IF($F$7>0,E19/$F$7,"") -> 0.26797346
B20: Cabe na sugestão de 30% do salário? | E20: =IF(E19<=$F$8,"Sim, suas metas cabem na sugestão.","Passou da sugestão: aumente os prazos ou reduza algum valor.") -> Sim, suas metas cabem na sugestão.
B22: Observações e premissas
B23: • As linhas de exemplo (viagem, reserva, casa, negócio e aposentadoria) são valores fictícios: troque pelos seus.
B24: • O rendimento mensal vem da aba Planilha2 (célula C21). Se você mudar lá, tudo aqui se atualiza.
B25: • O cálculo considera aportes no fim de cada mês e rendimento constante, a mesma lógica da função FV usada na Planilha2.
B26: • É uma projeção educativa: rendimentos reais variam e não há garantia de retorno.

Sheet Pausa na Carreira
B2: Pausa na Carreira
B3: Maternidade, cuidado com a família, mudança de emprego: a vida muda e às vezes o aporte precisa parar ou diminuir. Veja quanto uma pausa pesa no futuro e como recomeçar.
B5: Preencha (lilás, letra azul)
B6: Quanto invisto por mês hoje (R$) | C6: 500
B7: Horizonte total (anos) | C7: 20
B8: Depois de quantos anos começa a pausa? | C8: 5
B9: Duração da pausa (meses) | C9: 24
B10: Quanto invisto por mês ao retomar (R$) | C10: 250
B11: Rendimento mensal (da Planilha2) | C11: =Planilha2!C21 -> 0.01079
B13: Cálculo auxiliar (meses)
B14: Meses investindo antes da pausa | C14: =MIN(C8*12,C7*12) -> 60
B15: Meses de pausa | C15: =MIN(C9,C7*12-C14) -> 24
B16: Meses investindo depois da pausa | C16: =C7*12-C14-C15 -> 156
B17: =IF(C8*12+C9>C7*12,"Atenção: a pausa passa do horizonte total. Aumente os anos ou reduza a pausa.","")
B19: Cenário | C19: Patrimônio final | D19: Total que saiu do bolso | E19: Diferença para o cenário sem pausa
B20: A) Sem pausa | C20: =FV(C11,C7*12,-C6) -> 562599.2 | D20: =C6*C7*12 -> 120000 | E20: =C20-C20 -> 0
B21: B) Pausa e volto com o mesmo valor | C21: =FV(C11,C14,-C6)*(1+C11)^(C15+C16)+FV(C11,C16,-C6) -> 489974.24 | D21: =C6*C14+C6*C16 -> 108000 | E21: =C21-C20 -> -72624.963
B22: C) Pausa e volto com o valor menor | C22: =FV(C11,C14,-C6)*(1+C11)^(C15+C16)+FV(C11,C16,-C10) -> 389542.07 | D22: =C6*C14+C10*C16 -> 69000 | E22: =C22-C20 -> -173057.13
B24: Para recuperar: quanto guardar por mês ao retomar | C24: =IF(C16>0,-PMT(C11,C16,0,C20-FV(C11,C14,-C6)*(1+C11)^(C15+C16)),"") -> 680.78113
B25: Isso é quanto a mais por mês, comparado a hoje | C25: =IF(C24="","",C24-C6) -> 180.78113
B44: Observações e premissas
B45: • Os números preenchidos (R$ 500, 20 anos, pausa de 24 meses após 5 anos, retomada com R$ 250) são um exemplo fictício: troque pelos seus.
B46: • O rendimento mensal vem da aba Planilha2 (célula C21). Durante a pausa, o patrimônio já acumulado continua rendendo.
B47: • Aportes considerados no fim de cada mês, mesma lógica da função FV usada na Planilha2.
B48: • É uma projeção educativa: rendimentos reais variam e não há garantia de retorno.

Sheet Planilha-apoio
A2: CHAVE | B2: PERFIL | C2: TIPO DE FII | D2: % | H2: %
A3: =B3&"-"&C3 -> Conservador-PAPEL | B3: Conservador | C3: PAPEL | D3: 0.3 | G3: Moderado-TIJOLO | H3: =VLOOKUP(G3,$A:$D,4,) -> 0.35
A4: =B4&"-"&C4 -> Conservador-TIJOLO | B4: Conservador | C4: TIJOLO | D4: 0.5
A5: =B5&"-"&C5 -> Conservador-HIBRIDOS | B5: Conservador | C5: HIBRIDOS | D5: 0.1
A6: =B6&"-"&C6 -> Conservador-FOFs | B6: Conservador | C6: FOFs | D6: 0.1
A7: =B7&"-"&C7 -> Conservador-DESENVOLVIMENTO | B7: Conservador | C7: DESENVOLVIMENTO | D7: 0
A8: =B8&"-"&C8 -> Conservador-HOTELARIAS | B8: Conservador | C8: HOTELARIAS | D8: 0
A9: =B9&"-"&C9 -> Moderado-PAPEL | B9: Moderado | C9: PAPEL | D9: 0.32
A10: =B10&"-"&C10 -> Moderado-TIJOLO | B10: Moderado | C10: TIJOLO | D10: 0.35
A11: =B11&"-"&C11 -> Moderado-HIBRIDOS | B11: Moderado | C11: HIBRIDOS | D11: 0.08
A12: =B12&"-"&C12 -> Moderado-FOFs | B12: Moderado | C12: FOFs | D12: 0.05
A13: =B13&"-"&C13 -> Moderado-DESENVOLVIMENTO | B13: Moderado | C13: DESENVOLVIMENTO | D13: 0.1
A14: =B14&"-"&C14 -> Moderado-HOTELARIAS | B14: Moderado | C14: HOTELARIAS | D14: 0.1
A15: =B15&"-"&C15 -> Agressivo-PAPEL | B15: Agressivo | C15: PAPEL | D15: 0.6
... A20: =B20&"-"&C20 -> Agressivo-HOTELARIAS | B20: Agressivo | C20: HOTELARIAS | D20: 0.1
